vtds_platform_ubuntu/__init__.py
vtds_platform_ubuntu/private/__init__.py
vtds_platform_ubuntu/private/config.py
vtds_platform_ubuntu/private/platform.py
vtds_platform_ubuntu/private/config/README.md
vtds_platform_ubuntu/private/config/config.yaml
vtds_platform_ubuntu/private/config/test_overlay.yaml
vtds_platform_ubuntu/private/scripts/deploy_platform_to_blade.py
vtds_platform_ubuntu-0.0.14.dist-info/LICENSE
vtds_platform_ubuntu-0.0.14.dist-info/METADATA
vtds_platform_ubuntu-0.0.14.dist-info/WHEEL
vtds_platform_ubuntu-0.0.14.dist-info/top_level.txt
vtds_platform_ubuntu-0.0.14.dist-info/RECORD
